metaset/__init__.py
metaset/django_field.py
metaset-2.0.0.dist-info/LICENSE.txt
metaset-2.0.0.dist-info/METADATA
metaset-2.0.0.dist-info/WHEEL
metaset-2.0.0.dist-info/top_level.txt
metaset-2.0.0.dist-info/RECORD
