Metadata-Version: 2.1
Name: metaset
Version: 2.0.0
Summary: A container for dicts of sets - alternative to dictset
Home-page: https://github.com/Polyconseil/metaset
Download-URL: https://pypi.python.org/pypi/metaset/
Author: Polyconseil
Author-email: opensource+metaset@polyconseil.fr
License: BSD
Keywords: metaset,dictset,set,container
Classifier: Development Status :: 5 - Production/Stable
Classifier: Intended Audience :: Developers
Classifier: Natural Language :: English
Classifier: Programming Language :: Python
Classifier: License :: OSI Approved :: BSD License
Classifier: Topic :: Software Development :: Libraries :: Python Modules
Classifier: Operating System :: OS Independent
Classifier: Programming Language :: Python
Classifier: Programming Language :: Python :: 3
Classifier: Programming Language :: Python :: 3.8
Classifier: Programming Language :: Python :: 3.9
Classifier: Programming Language :: Python :: 3.10
Classifier: Programming Language :: Python :: 3.11
Classifier: Programming Language :: Python :: 3.12
Requires-Python: >=3.8
License-File: LICENSE.txt
